<?xml version="1.0" encoding="UTF-8"?>
<settings xsi:schemaLocation="http://maven.apache.org/SETTINGS/1.2.0 http://maven.apache.org/xsd/settings-1.2.0.xsd" xmlns="http://maven.apache.org/SETTINGS/1.2.0"
    xmlns:xsi="http://www.w3.org/2001/XMLSchema-instance">
  <servers>
    <server>
      <username>anialeher06@gmail.com</username>
      <password>cmVmdGtuOjAxOjE3MzIzMTU5OTc6c29PbW1tMFNSazEySlAwSjdNRHl4ZHBteTNj</password>
      <id>central</id>
    </server>
    <server>
      <username>anialeher06@gmail.com</username>
      <password>cmVmdGtuOjAxOjE3MzIzMTU5OTc6c29PbW1tMFNSazEySlAwSjdNRHl4ZHBteTNj</password>
      <id>snapshots</id>
    </server>
  </servers>
  <profiles>
    <profile>
      <repositories>
        <repository>
          <snapshots>
            <enabled>false</enabled>
          </snapshots>
          <id>central</id>
          <name>examenfinal1-libs-snapshot</name>
          <url>https://anahr18.jfrog.io/artifactory/examenfinal1-libs-snapshot</url>
        </repository>
        <repository>
          <snapshots />
          <id>snapshots</id>
          <name>examenfinal1-libs-snapshot</name>
          <url>https://anahr18.jfrog.io/artifactory/examenfinal1-libs-snapshot</url>
        </repository>
      </repositories>
      <pluginRepositories>
        <pluginRepository>
          <snapshots>
            <enabled>false</enabled>
          </snapshots>
          <id>central</id>
          <name>examenfinal1-libs-snapshot</name>
          <url>https://anahr18.jfrog.io/artifactory/examenfinal1-libs-snapshot</url>
        </pluginRepository>
        <pluginRepository>
          <snapshots />
          <id>snapshots</id>
          <name>examenfinal1-libs-snapshot</name>
          <url>https://anahr18.jfrog.io/artifactory/examenfinal1-libs-snapshot</url>
        </pluginRepository>
      </pluginRepositories>
      <id>artifactory</id>
    </profile>
  </profiles>
  <activeProfiles>
    <activeProfile>artifactory</activeProfile>
  </activeProfiles>
</settings>
